waelstow.py
waelstow-0.12.1.dist-info/licenses/LICENSE
waelstow-0.12.1.dist-info/METADATA
waelstow-0.12.1.dist-info/WHEEL
waelstow-0.12.1.dist-info/top_level.txt
waelstow-0.12.1.dist-info/RECORD
