Metadata-Version: 2.4
Name: waelstow
Version: 0.12.1
Summary: A small collection of tools for unit testing.  Includes 
Author-email: Christopher Trudeau <ctrudeau+pypi@arsensa.com>
License: The MIT License (MIT)
Project-URL: repository, https://github.com/cltrudeau/waelstow
Project-URL: documentation, https://waelstow.readthedocs.io/en/latest/
Keywords: test,testing,unit test,unittest,test runner
Classifier: Development Status :: 4 - Beta
Classifier: Environment :: Web Environment
Classifier: Intended Audience :: Developers
Classifier: License :: OSI Approved :: MIT License
Classifier: Operating System :: OS Independent
Classifier: Programming Language :: Python :: 3.9
Classifier: Programming Language :: Python :: 3.10
Classifier: Programming Language :: Python :: 3.11
Classifier: Programming Language :: Python :: 3.12
Classifier: Programming Language :: Python :: 3.13
Classifier: Topic :: Software Development :: Libraries :: Application Frameworks
Classifier: Topic :: Software Development :: Libraries :: Python Modules
Requires-Python: >=3.9
License-File: LICENSE
Provides-Extra: build
Requires-Dist: build==1.2.2.post1; extra == "build"
Requires-Dist: twine==6.1.0; extra == "build"
Provides-Extra: dev
Requires-Dist: coverage==7.8.0; extra == "dev"
Requires-Dist: nox==2025.2.9; extra == "dev"
Requires-Dist: pudb==2024.1.3; extra == "dev"
Requires-Dist: pyflakes==3.3.2; extra == "dev"
Requires-Dist: Sphinx==8.2.3; extra == "dev"
Requires-Dist: sphinx-rtd-theme==3.0.2; extra == "dev"
Requires-Dist: twine==6.1.0; extra == "dev"
Dynamic: license-file
